{"arms":[{"arm_name":"M0_principal_only","canonical_reconstruction_rate":null,"exact_target_accuracy":0.9514563106796117,"final_loss_ledger_reconciliation_error":0.0,"final_reported_loss":21.599563598632812,"fixed_corruption_legal_nll":7.5223306550056135,"fixed_corruption_raw_nll":21.96682184934616,"honest_caveats":[],"lr":0.0003,"seed":0,"steps":3,"trainable_parameter_count":66594,"wall_seconds":2.5140562009764835},{"arm_name":"M1_current_recipe","canonical_reconstruction_rate":null,"exact_target_accuracy":0.9514563106796117,"final_loss_ledger_reconciliation_error":9.537e-07,"final_reported_loss":41.00300979614258,"fixed_corruption_legal_nll":7.504294084188969,"fixed_corruption_raw_nll":21.99333307147026,"honest_caveats":[],"lr":0.0003,"seed":0,"steps":3,"trainable_parameter_count":66594,"wall_seconds":1.7761585949920118}],"claim_class":"wiring","corruption_suite":{"cases":[{"case_id":"smoke_callout_01::one_hole","condition":"one_hole","diffusion_time":0.006535947712418301,"legal_candidates_sha256":null,"noisy_ids":[0,1,2,3,4,5,6,7,-1,9,10,11,12],"policy":"fixed_mask","predict_mask":[false,false,false,false,false,false,false,false,true,false,false,false,false],"record_id":"smoke_callout_01","row_sha256":"7c7a257cc2ad5ebd20143ef6b61a61006e173f3a5b81696e1336a8984b075488","seed":261,"target_ids":[0,1,2,3,4,5,6,7,8,9,10,11,12]},{"case_id":"smoke_callout_01::low_noise","condition":"low_noise","diffusion_time":0.1,"legal_candidates_sha256":null,"noisy_ids":[0,1,-1,3,4,5,6,7,8,9,10,11,12],"policy":"fixed_mask","predict_mask":[false,false,true,false,false,false,false,false,false,false,false,false,false],"record_id":"smoke_callout_01","row_sha256":"c66396dd294a44a3cf24481f549e6a384c75fec65d17f48f4e6e9e04000cc013","seed":261,"target_ids":[0,1,2,3,4,5,6,7,8,9,10,11,12]},{"case_id":"smoke_callout_01::medium_noise","condition":"medium_noise","diffusion_time":0.5,"legal_candidates_sha256":null,"noisy_ids":[0,-1,2,3,-1,5,-1,-1,8,-1,10,-1,12],"policy":"fixed_mask","predict_mask":[false,true,false,false,true,false,true,true,false,true,false,true,false],"record_id":"smoke_callout_01","row_sha256":"5d2f84dd779ae3507bef4bf2c0f5a262a5c4212d1c013ad38269cd3a553b28d4","seed":261,"target_ids":[0,1,2,3,4,5,6,7,8,9,10,11,12]},{"case_id":"smoke_callout_01::all_mask","condition":"all_mask","diffusion_time":1.0,"legal_candidates_sha256":null,"noisy_ids":[-1,-1,-1,-1,-1,-1,-1,-1,-1,-1,-1,-1,-1],"policy":"fixed_mask","predict_mask":[true,true,true,true,true,true,true,true,true,true,true,true,true],"record_id":"smoke_callout_01","row_sha256":"92c6970eec165b3e059b103fd167462658c0a5e33b375cacc255ddaf0d55de40","seed":261,"target_ids":[0,1,2,3,4,5,6,7,8,9,10,11,12]},{"case_id":"smoke_hero_01::one_hole","condition":"one_hole","diffusion_time":0.006535947712418301,"legal_candidates_sha256":null,"noisy_ids":[0,1,2,3,4,5,-1,7,8,9,10,11,12,13,14,15,16,17,18,19,20,21,22],"policy":"fixed_mask","predict_mask":[false,false,false,false,false,false,true,false,false,false,false,false,false,false,false,false,false,false,false,false,false,false,false],"record_id":"smoke_hero_01","row_sha256":"8fb3164f75b424c039a795140c59b117fd4e3671a7b9f312ce68f0304b389d6a","seed":261,"target_ids":[0,1,2,3,4,5,6,7,8,9,10,11,12,13,14,15,16,17,18,19,20,21,22]},{"case_id":"smoke_hero_01::low_noise","condition":"low_noise","diffusion_time":0.1,"legal_candidates_sha256":null,"noisy_ids":[0,1,2,-1,4,5,6,7,8,9,10,11,12,13,14,15,-1,17,18,19,20,21,22],"policy":"fixed_mask","predict_mask":[false,false,false,true,false,false,false,false,false,false,false,false,false,false,false,false,true,false,false,false,false,false,false],"record_id":"smoke_hero_01","row_sha256":"b282d39af8539ecbe07f6ee6a22c1c5cd914a98fd55a10683b4e51088bfe9a5f","seed":261,"target_ids":[0,1,2,3,4,5,6,7,8,9,10,11,12,13,14,15,16,17,18,19,20,21,22]},{"case_id":"smoke_hero_01::medium_noise","condition":"medium_noise","diffusion_time":0.5,"legal_candidates_sha256":null,"noisy_ids":[0,-1,2,3,-1,-1,-1,-1,8,-1,10,11,12,-1,14,15,-1,-1,18,-1,-1,-1,22],"policy":"fixed_mask","predict_mask":[false,true,false,false,true,true,true,true,false,true,false,false,false,true,false,false,true,true,false,true,true,true,false],"record_id":"smoke_hero_01","row_sha256":"f6205ae850f8f814e4d91d5304f4e07b362b3f105d17e1d766c6638607689b5d","seed":261,"target_ids":[0,1,2,3,4,5,6,7,8,9,10,11,12,13,14,15,16,17,18,19,20,21,22]},{"case_id":"smoke_hero_01::all_mask","condition":"all_mask","diffusion_time":1.0,"legal_candidates_sha256":null,"noisy_ids":[-1,-1,-1,-1,-1,-1,-1,-1,-1,-1,-1,-1,-1,-1,-1,-1,-1,-1,-1,-1,-1,-1,-1],"policy":"fixed_mask","predict_mask":[true,true,true,true,true,true,true,true,true,true,true,true,true,true,true,true,true,true,true,true,true,true,true],"record_id":"smoke_hero_01","row_sha256":"42d26548066c01a22767ec6bd43e38e99ee667dff4ba6b8828ff8dc253c7440b","seed":261,"target_ids":[0,1,2,3,4,5,6,7,8,9,10,11,12,13,14,15,16,17,18,19,20,21,22]},{"case_id":"smoke_button_01::one_hole","condition":"one_hole","diffusion_time":0.006535947712418301,"legal_candidates_sha256":null,"noisy_ids":[0,1,2,3,4,-1,6,7,8,9],"policy":"fixed_mask","predict_mask":[false,false,false,false,false,true,false,false,false,false],"record_id":"smoke_button_01","row_sha256":"7ae22e83bddc33e6ba95b63aeb498f272d557e67a251b30c70bc7fa0fe2664ca","seed":261,"target_ids":[0,1,2,3,4,5,6,7,8,9]},{"case_id":"smoke_button_01::low_noise","condition":"low_noise","diffusion_time":0.1,"legal_candidates_sha256":null,"noisy_ids":[-1,1,2,3,4,5,6,7,8,9],"policy":"fixed_mask","predict_mask":[true,false,false,false,false,false,false,false,false,false],"record_id":"smoke_button_01","row_sha256":"4a7b67de831d0da6bae036f2b663678053a7fb3cd8d77f483a76ba9f712440af","seed":261,"target_ids":[0,1,2,3,4,5,6,7,8,9]},{"case_id":"smoke_button_01::medium_noise","condition":"medium_noise","diffusion_time":0.5,"legal_candidates_sha256":null,"noisy_ids":[-1,-1,-1,-1,4,5,6,7,-1,9],"policy":"fixed_mask","predict_mask":[true,true,true,true,false,false,false,false,true,false],"record_id":"smoke_button_01","row_sha256":"b0c06d91f773c0c8eb9bad5fcc577e4df6107172df153a38696b6915cf45c9af","seed":261,"target_ids":[0,1,2,3,4,5,6,7,8,9]},{"case_id":"smoke_button_01::all_mask","condition":"all_mask","diffusion_time":1.0,"legal_candidates_sha256":null,"noisy_ids":[-1,-1,-1,-1,-1,-1,-1,-1,-1,-1],"policy":"fixed_mask","predict_mask":[true,true,true,true,true,true,true,true,true,true],"record_id":"smoke_button_01","row_sha256":"8de01d314d0bd35e3e4590396492152167116c7c24010c54659dd0a28870b878","seed":261,"target_ids":[0,1,2,3,4,5,6,7,8,9]}],"conditions":["one_hole","low_noise","medium_noise","all_mask"],"record_ids":["smoke_callout_01","smoke_hero_01","smoke_button_01"],"schema_version":"MemorizationCorruptionSuiteV1","source_corpus_sha256":"d49f68483273b41115667d3611aafc21e77658aee404b7706824227092a62493","suite_id":"memorization_3_v1_20260721","timestamp":"2026-07-21T10:12:45.927590Z"},"disposition":"inconclusive","disposition_rationale":"No arm reached the strict fixture memorization thresholds (exact target accuracy >= 0.99 and ledger reconciliation error < 1e-3). This is expected for a tiny diagnostic fixture; it is not a falsification.","experiment_id":"slm261-memorization-probe","falsifier":"Principal loss cannot fall below 0.10 nats/token, exact target accuracy cannot exceed 0.99, canonical reconstruction cannot exceed 0.98, or the loss ledger fails reconciliation.","honest_caveats":["Fixture-only diagnostic: tiny model, tiny corpus, CPU run, no ship claim.","VSD0-01 semantic scorer prerequisite is not enforced by this fixture.","Candidate-normalized CE (M2) is not implemented in this iteration.","Exact canonical reconstruction is measured by string match, not the full binding-aware meaning pipeline."],"hypothesis":"A correctly wired TwoTower trainer can memorize a small verified corpus: principal masked CE falls, exact target accuracy rises, and every active loss term reconciles with the reported total.","matrix_set":"slm261_memorization_probe","matrix_version":"vsd0-02-v1","n_arms":2,"n_records":3,"run_id":"slm261-79f2e77b","schema":"MemorizationProbeManifestV1","status":"fixture","timestamp":"2026-07-21T10:12:48.792805Z","version_stamp":{"code_commit":"d10d47aca0c0559d7ccfd7717ee950134e2e0e90","code_dirty":true,"components":{"harness.experiments":"v62","model.twotower":"v84"},"stamp_schema":"version_stamp/v1","stamped_at":"2026-07-21T10:12:48.792788+00:00"}}