{
  "schema_version": 1,
  "experiment_ids": [
    "E480",
    "E481"
  ],
  "date": "2026-07-18",
  "status": "complete",
  "checkpoint": {
    "run_id": "e396-balanced-type-head-continuation-r1",
    "sha256": "feefa0564490bd1db42f79ff710143ad8ed07ab9e4e324f2744a30f8c2f2eee0"
  },
  "data": {
    "version": "e451_root_binder_v1",
    "suite": "rico_held",
    "eval_offset": 960,
    "n": 1,
    "record_id": "rico_hf_test_2249"
  },
  "runs": [
    {
      "experiment_id": "E480",
      "run_id": "e480-e396-slider-schema-row960-r1",
      "instrumented": false,
      "elapsed_seconds": 6.3
    },
    {
      "experiment_id": "E481",
      "run_id": "e481-e396-slider-raw-choice-row960-r1",
      "instrumented": true,
      "elapsed_seconds": 5.4
    }
  ],
  "result": {
    "meaningful_program_rate": 1.0,
    "placeholder_fidelity": 1.0,
    "structural_similarity": 0.7292,
    "component_type_recall": 1.0,
    "reward_score": 0.997,
    "failure_count": 0,
    "fallback_count": 0,
    "decode_timeout_count": 0,
    "invalid_output": "Slider(\"item\", \"continuous\", \"nnu\", 40)",
    "raw_numeric_tokens": [
      "LIT_NUM",
      "B:6e",
      "B:6e",
      "B:75",
      "LIT_END"
    ]
  },
  "timing": {
    "external_timeout_seconds": 290,
    "external_kill_after_seconds": 10,
    "completed_normally": true
  },
  "verdict": "Reject numeric-frame behavior; deterministic codec fix required."
}
